# 메모리 관리와 좋은 습관

> 이 문서는 아래 첨부한 아티클의 요약본입니다.
> [파이썬 - 메모리 관리와 좋은 습관](https://yomangstartup.tistory.com/105) 

## 파이썬 메모리 관리에 대해 배워야하는 이유

파이썬은 메모리를 자동으로 관리해주는 언어이다.
그러나 파이썬 최적화 코드에 지식이 없다면 안 좋은 코드 습관이 생기게 된다.
파이썬에서 메모리를 관리하는 방법을 알아야, 최적화된 코드를 작성하는 좋은 습관을 들일 수 있다.

## 파이썬이 실행되는 방식

파이썬은 컴파일러와 인터프린터를 혼합하여 사용한다.

**1) 컴파일**

파이썬 코드를 작성하고 실행 버튼을 누르면, 파이썬 코드는 0과 1로 이루어진 **바이트 코드**로 변환된다.
이러한 과정을 **컴파일**이라고 한다.

**2) 인터프린팅, 런타임**

변환된 바이트 코드는 메모리에 올라가 차례차례 실행된다.
이 과정을 **인터프린팅** 혹은 **런타임**이라고 한다.

**3) 파이썬 가상 머신**

런타임 때 파이썬은 python virtual machine이라는 가상 컴퓨터에서 바이트 코드를 실행한다.
*외부 모듈*의 경우, 가상 머신이 만들어지고 바이트 코드를 해석할 때 추가된다.

**4) 파이썬 인터프린터**

이렇게 파이썬을 실행하는 프로그램은 여러 가지가 있다

- **cpython** (파이썬 설치 시 기본적으로 제공하는 인터프린터)
- pypy
- ironpython

## cpython

파이썬을 실행하는 대표적인 인터프리터인 cpython으로 파이썬 인터프리터의 동작 방식을 살펴본다.

### cpython의 메모리 관리

컴퓨터 공학에서 메모리 관리 중 가장 중요한 부분은 **메모리 할당**이다.

**정적 메모리 할당**

- 코드들이 컴파일 시간에 할당되는 것
- stack 자료구조 사용 : 프로그램이 끝날 때까지 stack에 저장된 데이터는 사라지지 않는다.

**동적 메모리 할당**

- 코드가 실행되고 나서 메모리에 할당되는 것
- heap 자료구조 사용 : 데이터가 필요하지 않으면 메모리에서 제거할 수 있다.

**cpython에서 메모리를 할당하는 방식**

- 정적 메모리 : 정의된 함수, 변수의 이름
- 동적 메모리 (heap) : 모든 오브젝트들이 들어간다. (오브젝트 - 메모리에 존재하는 실제 값)
- 실행 순서 : 실행 버튼 클릭 → 기본적인 세팅 → 위에서 아래로 한 줄씩 읽으며 코드를 이해
- 변수를 메모리 주소값을 이용해 구현 : 변수를 스택에 저장 → 변수에 할당된 값을 힙영역에 오브젝트로 저장 → 힙 영역의 메모리 주소를, 스택에서 변수와 메모리 주소를 함께 저장 (참조)
- 힙 영역에서 어떠한 변수도 참조하고 있지 않는 오브젝트는 삭제하여 메모리 낭비를 줄인다.

## mutable vs immutable

파이썬에서는 오브젝트 종류, 데이터 타입에 따라 메모리 관리하는 방식이 다르다.

### immutable 타입

immutable 타입의 오브젝트는 메모리에 올라가면 변경이 불가하다.

메모리에서는 오브젝트는 변하지 않고 reference만 변한다 = **interning**

**immutable 오브젝트**

- int
- float
- bool
- str
- tuple
- unicode
- bytes

```py
a = 1

print(a) # 1
print(id(a)) # 1684245184752

a = 2

print(a) # 2
print(id(a)) # 1684245184784 -> 메모리 주소값이 변경됨
```

```py
a = (1, 2, 3, 4, 5)

print(a) # (1, 2, 3, 4, 5)
print(id(a)) # 1684324081936

a *= 2

print(a) # (1, 2, 3, 4, 5, 1, 2, 3, 4, 5)
print(id(a)) # 1684325254848 -> 메모리 주소값이 변경됨
```

### mutable 타입

mutable 타입은 오브젝트의 메모리 주소만 알면 변경이 가능하다.

**mutable 오브젝트**

- list
- bytearray
- collection
- deque
- dictionary

```py
a = [1, 2, 3, 4, 5]

print(a) # [1, 2, 3, 4, 5]
print(id(a)) # 1684325466560

a *= 2

print(a) # [1, 2, 3, 4, 5, 1, 2, 3, 4, 5]
print(id(a)) # 1684325466560 -> 메모리 주소값이 같음
```

## 컴파일 시 저장되는 것 vs 런타임 시 저장되는 것

- ex_1 함수 : 파이썬 오브젝트들을 힙 영역에 효율적으로 저장한 상태
- ex_2 함수 : 문자열을 로컬 변수를 저장해서 BINARY_ADD 연산이 실행되고, 이는 런타임 과정에서 실행된다
- 로컬 변수의 경우, 함수가 실행될 떄 생성 / 함수가 종료될 때 삭제된다. 함수의 내부는 런타임 과정에 실행되기 때문에 함수 내부의 로컬 변수는 런타임 과정에 실행된다.
- 결론? : 계산 없이 실행될 수 있는 코드를 계산 과정을 굳이굳이 넣어서 바보코드가 됨

```py
import dis

def ex_1():
    return 'asdf' is 'as' + 'df'

dis.dis(ex_1)

# 오브젝트 위치가 1로 같다
#   4           0 LOAD_CONST               1 ('asdf')
#               2 LOAD_CONST               1 ('asdf')
#               4 IS_OP                    0
#               6 RETURN_VALUE

def ex_2():
    qwer = 'df'
    return 'asdf' is 'as' + qwer

dis.dis(ex_2)

# 'df'를 qwer 변수에 저장
#  15           0 LOAD_CONST               1 ('df')
#               2 STORE_FAST               0 (qwer)

# 'as'와 qwer를 더하면 스트링 연산 BINARY_ADD 동작이 추가됨
#  16           4 LOAD_CONST               2 ('asdf')
#               6 LOAD_CONST               3 ('as')
#               8 LOAD_FAST                0 (qwer)
#              10 BINARY_ADD
#              12 IS_OP                    0
#              14 RETURN_VALUE
```

## 좋은 습관 만들기

### 제너레이터 사용하기

제너레이터는 아이템을 한 번에 리턴하지 않고, yield를 통해 하나씩 리턴한다.

아래의 코드에서, silver 함수는 리스트 a와 b를 동시에 저장해 gold 함수보다 메모리를 2배 더 많이 차지하게 된다.

```py
import dis


def silver():
    a = [1, 2, 3, 4]
    b = []

    for ele in a:
        b.append(ele * 2)
    
    return b

dis.dis(silver)

#   5           0 BUILD_LIST               0
#               2 LOAD_CONST               1 ((1, 2, 3, 4))
#               4 LIST_EXTEND              1
#               6 STORE_FAST               0 (a)

#   6           8 BUILD_LIST               0
#              10 STORE_FAST               1 (b)

#   8          12 LOAD_FAST                0 (a)
#              14 GET_ITER
#         >>   16 FOR_ITER                 9 (to 36)
#              18 STORE_FAST               2 (ele)

#   9          20 LOAD_FAST                1 (b)
#              22 LOAD_METHOD              0 (append)
#              24 LOAD_FAST                2 (ele)
#              26 LOAD_CONST               2 (2)
#              28 BINARY_MULTIPLY
#              30 CALL_METHOD              1
#              32 POP_TOP
#              34 JUMP_ABSOLUTE            8 (to 16)

#  11     >>   36 LOAD_FAST                1 (b)
#              38 RETURN_VALUE
```


```py
import dis

def gold():
    a = [1, 2, 3, 4]

    for ele in a:
        yield ele * 2

dis.dis(gold)

#               0 GEN_START                0

#   4           2 BUILD_LIST               0
#               4 LOAD_CONST               1 ((1, 2, 3, 4))
#               6 LIST_EXTEND              1
#               8 STORE_FAST               0 (a)

#   6          10 LOAD_FAST                0 (a)
#              12 GET_ITER
#         >>   14 FOR_ITER                 7 (to 30)
#              16 STORE_FAST               1 (ele)

#   7          18 LOAD_FAST                1 (ele)
#              20 LOAD_CONST               2 (2)
#              22 BINARY_MULTIPLY
#              24 YIELD_VALUE
#              26 POP_TOP
#              28 JUMP_ABSOLUTE            7 (to 14)

#   6     >>   30 LOAD_CONST               0 (None)
#              32 RETURN_VALUE
```

### 로컬 함수에 다시 선언하기

파이썬은 글로벌보다 로컬 변수가 훨씬 빠르다.
함수를 로컬 변수에 다시 정의하면 빠르게 사용할 수 있다.

자세한 이유는 [여기](https://yomangstartup.tistory.com/112)

```py
def silver():
    print("asdf")

def gold():
    pri = print
    pri("qwer")
```

### itertools 사용

추가 공부! 